README.md
setup.cfg
setup.py
graphene_validator/__init__.py
graphene_validator/decorators.py
graphene_validator/errors.py
graphene_validator/schema.py
graphene_validator/utils.py
graphene_validator.egg-info/PKG-INFO
graphene_validator.egg-info/SOURCES.txt
graphene_validator.egg-info/dependency_links.txt
graphene_validator.egg-info/requires.txt
graphene_validator.egg-info/top_level.txt