Metadata-Version: 2.1
Name: graphene-validator
Version: 0.0.1
Summary: An input validation library for Graphene
Home-page: https://github.com/chpmrc/graphene-validator
Author: Marco Chiappetta
License: MIT
Platform: UNKNOWN
Classifier: License :: OSI Approved :: MIT License
Classifier: Programming Language :: Python :: 3
Classifier: Programming Language :: Python :: 3.7
